bmcs_matmod/__init__.py
bmcs_matmod/__version__.py
bmcs_matmod/api.py
bmcs_matmod/version.py
bmcs_matmod/design_description/01_gsm_presentation_framework.md
bmcs_matmod/design_description/02_gsm_presentation_framework_refined.md
bmcs_matmod/design_description/03_gsm_presentation_framework_refined_aiida.md
bmcs_matmod/design_description/04_gsm_presentation_framework_parametric_tools_comparison.md
bmcs_matmod/design_description/05_material_research_management_platform_recommendation.md
bmcs_matmod/design_description/06_structural_member_design_IRD_platform_recommendation.md
bmcs_matmod/design_description/07_aiida_and_project_management.md
bmcs_matmod/design_description/08_open_source_project_management.md
bmcs_matmod/design_description/09_open_source_project_management_openproject_comparison.md
bmcs_matmod/design_description/10_lims_eln_review.md
bmcs_matmod/design_description/11_material_research_process_uml.md
bmcs_matmod/design_description/11_material_research_process_uml.puml
bmcs_matmod/design_description/12_material_research_process_uml_activity_example.puml
bmcs_matmod/design_description/13_material_research_process_refined_activity.md
bmcs_matmod/design_description/13_material_research_process_refined_activity.puml
bmcs_matmod/design_description/14_material_research_process_state_diagram.puml
bmcs_matmod/design_description/14_material_research_process_state_diagram_explanation.md
bmcs_matmod/design_description/15_aiida_for_parallel_binder_characterization.md
bmcs_matmod/design_description/16_gsm_aiida_integration_architecture.md
bmcs_matmod/design_description/17_fatrescon_workchain_architecture.md
bmcs_matmod/design_description/18_fatrescon_development_scenarios_aiidalab_local.md
bmcs_matmod/design_description/aiida_material_research_workflow_example.ipynb
bmcs_matmod/gsm_lagrange/__init__.py
bmcs_matmod/gsm_lagrange/gsm_lagrange.puml
bmcs_matmod/gsm_lagrange/aiida_plugin/__init__.py
bmcs_matmod/gsm_lagrange/aiida_plugin/calculations.py
bmcs_matmod-0.0.10a0.dist-info/LICENSE
bmcs_matmod-0.0.10a0.dist-info/METADATA
bmcs_matmod-0.0.10a0.dist-info/WHEEL
bmcs_matmod-0.0.10a0.dist-info/entry_points.txt
bmcs_matmod-0.0.10a0.dist-info/top_level.txt
bmcs_matmod-0.0.10a0.dist-info/RECORD
