Metadata-Version: 2.2
Name: bmcs_matmod
Version: 0.0.10a0
Summary: Suite of utilities for material model development.
Home-page: https://github.com/bmcs-group/bmcs_matmod
Author: BMCS-Group
Author-email: BMCS-Group <rostislav.chudoba@rwt-aachen.de>
License: MIT License
Project-URL: Homepage, https://github.com/bmcs-group/bmcs_matmod
Requires-Python: >=3.6.0
License-File: LICENSE
Requires-Dist: bmcs_utils
Requires-Dist: numpy
Requires-Dist: sympy
Requires-Dist: traits
Provides-Extra: dev
Requires-Dist: pytest; extra == "dev"
Requires-Dist: pytest-cov; extra == "dev"
Requires-Dist: twine; extra == "dev"
Dynamic: author
Dynamic: home-page
Dynamic: requires-python
